Workbook
Name IN_File名: #REF!
Name IN_コミットリビジョン: #REF!
Name IN_サーバー: #REF!
Name IN_同期: #REF!
Name IN_配信環境: #REF!
Name UP区分: #REF!
Name サーバー: #REF!
Name 修正区分: #REF!
Name 同期サーバ: #REF!
Name 配信環境: #REF!

Sheet まとめ
A1: UPDATEリストで重複（資源が競合してる場合は、資源が重複しないように、案件名を一緒に記載していない）
B2: (46)大和ネクスト銀行でのマイナンバー受入確認義務化に関する追加開発
B3: (44)大引け注文対応
C4: WEB-INF/classes/webbroker3/web/define/CodeValueConst.class
D5: '0D
D6: 'P0
D7: '09
D8: '0C
D9: '0H
D10: '52
D11: '0F
D12: '0X
D13: '0G
B14: (44)大引け注文対応
B15: 大和ネクスト銀行でのマイナンバー受入確認義務化に関する追加開発
C16: WEB-INF/lib/plug-web3-common.jar
D17: '0H
D18: '52
B19: ORA-01861（日付形式の暗黙の型変換）の明示変換化_3/22実施
C20: WEB-INF/lib/plug-web3-xbfeq.jar
D21: '0H
D22: '52
A24: 棚卸しで差分が出ていてUPDATEリストに記載がない
B25: (0F)投資信託銘柄検索機能の追加
C26: WEB-INF/lib/plug-web3-xbmf.jar
D27: '0D
D28: '44
D29: '0X
D30: '46
B31: ※ 内藤には ＋ (0D)定時定額金額チェック仕様の改善
B33: ログイン時多要素認証の導入_API対応
C34: WEB-INF/classes/webbroker3/web/beans/rc/login/WEB3RcLoginAuthCodeConfirmInputBean.class
C35: WEB-INF/classes/webbroker3/web/factory/rc/login/AccountLoginLcFactory.class
C36: WEB-INF/classes/webbroker3/web/factory/rc/login/LoginAuthCodeConfirmInputFactory.class
D37: '0D
D38: 'P0
D39: '09
D40: '44
D41: '0C
D42: '0H
D43: '52
D44: '0F
D45: '0X
D46: '0G
B48: ログイン時多要素認証の導入_脆弱性対応
C49: WEB-INF/lib/web3base.jar
D50: 'P0
D51: '09
D52: '0C
D53: '0H
D54: '52
D55: '0G
A56: UPDATEリストの対象にフィデリティ（撤退会社）がある
B57: ■(0D)中国株売買画面のリアルタイム株価パーツ入替
B58: ■(44)大引け注文対応
B59: ■大和ネクスト銀行でのマイナンバー受入確認義務化に関する追加開発
B60: ■投資信託銘柄検索機能の追加
B61: ログイン時多要素認証の導入_API対応
B62: ■ログイン時多要素認証の導入
B63: ■ログイン時多要素認証の導入_脆弱性対応

Sheet wb4_20250810_pr
A1: wb4_pr
A2: コード | B2: ファイル | C2: 本番 | D2: SVN | E2: 差異概要 | F2: 備考／差分発生日 | G2: 原因 | I2: 対応 | M2: 確認 | S2: 承認 | W2: 1：UPDATEリストに記載あり
C3: 20250810 | D3: 1713128 | G3: 種別 | H3: 詳細 | I3: 概要 | J3: 担当者 | K3: 完了予定日 | L3: 完了日 | M3: 判定 | N3: 概要 | O3: 案件 | P3: 案件担当者 | Q3: 記載者 | R3: 記載日 | S3: 承認者 | T3: 承認日 | U3: 備考 | W3: UPDATEリストチェック | Z3: memo
A4: 0D wb | B4: 0D/pc/aio/WEB3AioCashoutCancelList_inc.jsp | C4: ○ | D4: ○ | E4: ファイルが違う | F4: 20210411 新規差分 | M4: 確認 | N4: コミット漏れ | O4: 3/13実施 (0D)WB4レベルアップ対応 他社展開(0D) 出金取消対応 tar作成 | P4: 黒須代理 | W4: =COUNTIF(内藤証券!U:U,B4) -> 0 | Z4: jsp
A5: 0D wb | B5: 0D/sp/WEB3Index_stop.jsp | C5: - | D5: ○ | E5: 本番ファイルがない | F5: 20210411 新規差分 | G5: 90 | H5: 2021/6/2 関谷 概要欄に記載の通り、チェック不要としてよいのではないでしょうか？ | I5: - | J5: - | K5: - | L5: - | N5: [OS更改前除外対象]trunk削除？cwには本番あり、cw本番削除？ （障害時にSPを停止するソースのため、意図的に本番にあげていないソース[若松]） | O5: 金融OS更改 | R5: - | W5: =COUNTIF(内藤証券!U:U,B5) -> 0 | Z5: jsp
A6: 0D wb | B6: WEB-INF/classes/webbroker3/web/beans/application.xml | C6: ○ | D6: ○ | E6: ファイルが違う | F6: 20250105 新規差分 | N6: 他社展開前 | O6: (46)大和ネクスト銀行でのマイナンバー受入確認義務化に関する追加開発 | Q6: DIS山田 | R6: 45814 | W6: =COUNTIF(内藤証券!U:U,B6) -> 0
A7: 0D wb | B7: WEB-INF/classes/webbroker3/web/beans/pc/accinfo/WEB3AccInfoFinancialSearchBean2.class | C7: - | D7: ○ | E7: 本番ファイルがない | F7: 20250406 新規差分 | N7: 他社展開前 | O7: (46)大和ネクスト銀行でのマイナンバー受入確認義務化に関する追加開発 | Q7: DIS山田 | R7: 45756 | W7: =COUNTIF(内藤証券!U:U,B7) -> 0
A8: 0D wb | B8: WEB-INF/classes/webbroker3/web/beans/pc/accinfo/WEB3PcAccInfoMynumberAcceptInfoRegistCompleteBean.class | C8: - | D8: ○ | E8: 本番ファイルがない | F8: 20250406 新規差分 | N8: 他社展開前 | O8: (46)大和ネクスト銀行でのマイナンバー受入確認義務化に関する追加開発 | Q8: DIS山田 | R8: 45756 | W8: =COUNTIF(内藤証券!U:U,B8) -> 0
A9: 0D wb | B9: WEB-INF/classes/webbroker3/web/beans/pc/accinfo/WEB3PcAccInfoMynumberAcceptInfoRegistConfirmBean.class | C9: - | D9: ○ | E9: 本番ファイルがない | F9: 20250406 新規差分 | N9: 他社展開前 | O9: (46)大和ネクスト銀行でのマイナンバー受入確認義務化に関する追加開発 | Q9: DIS山田 | R9: 45756 | W9: =COUNTIF(内藤証券!U:U,B9) -> 0
A10: 0D wb | B10: WEB-INF/classes/webbroker3/web/beans/pc/accinfo/WEB3PcAccInfoMynumberAcceptInfoRegistInputBean.class | C10: - | D10: ○ | E10: 本番ファイルがない | F10: 20250406 新規差分 | N10: 他社展開前 | O10: (46)大和ネクスト銀行でのマイナンバー受入確認義務化に関する追加開発 | Q10: DIS山田 | R10: 45756 | W10: =COUNTIF(内藤証券!U:U,B10) -> 0
A11: 0D wb | B11: WEB-INF/classes/webbroker3/web/beans/rc/login/WEB3RcLoginAuthCodeConfirmInputBean.class | C11: - | D11: ○ | E11: 本番ファイルがない | F11: 20250810 新規差分 | N11: 他社展開前 | O11: ログイン時多要素認証の導入_API対応 | Q11: DIS山田 | R11: 45883 | W11: =COUNTIF(内藤証券!U:U,B11) -> 0
A12: 0D wb | B12: WEB-INF/classes/webbroker3/web/define/AD_OR_ParameterConst.class | C12: ○ | D12: ○ | E12: ファイルが違う | F12: 20250406 新規差分 | N12: 他社展開前 | O12: (44)大引け注文対応 | Q12: DIS山田 | R12: 45756 | W12: =COUNTIF(内藤証券!U:U,B12) -> 0
A13: 0D wb | B13: WEB-INF/classes/webbroker3/web/define/AI_ParameterConst.class | C13: ○ | D13: ○ | E13: ファイルが違う | F13: 20250209 新規差分 | N13: 他社展開前 | O13: (46)大和ネクスト銀行でのマイナンバー受入確認義務化に関する追加開発 | Q13: DIS山田 | R13: 45814 | W13: =COUNTIF(内藤証券!U:U,B13) -> 0
A14: 0D wb | B14: WEB-INF/classes/webbroker3/web/define/CodeValueConst.class | C14: ○ | D14: ○ | E14: ファイルが違う | F14: 20250209 新規差分 | N14: 他社展開前 | O14: (46)大和ネクスト銀行でのマイナンバー受入確認義務化に関する追加開発 (44)大引け注文対応 | Q14: DIS山田 | R14: 45814 | W14: =COUNTIF(内藤証券!U:U,B14) -> 1 | Z14: CodeValueConst.class 記載重複
A15: 0D wb | B15: WEB-INF/classes/webbroker3/web/define/EQ_ParameterConst.class | C15: ○ | D15: ○ | E15: ファイルが違う | F15: 20250406 新規差分 | N15: 他社展開前 | O15: (44)大引け注文対応 | Q15: DIS山田 | R15: 45756 | W15: =COUNTIF(内藤証券!U:U,B15) -> 0
A16: 0D wb | B16: WEB-INF/classes/webbroker3/web/define/MF_ParameterConst.class | C16: ○ | D16: ○ | E16: ファイルが違う | F16: 20250810 新規差分 | N16: 他社展開前 | O16: (0F)投資信託銘柄検索機能の追加 | Q16: DIS山田 | R16: 45883 | W16: =COUNTIF(内藤証券!U:U,B16) -> 0
A17: 0D wb | B17: WEB-INF/classes/webbroker3/web/define/MR_ParameterConst.class | C17: ○ | D17: ○ | E17: ファイルが違う | F17: 20250406 新規差分 | N17: 他社展開前 | O17: (44)大引け注文対応 | Q17: DIS山田 | R17: 45756 | W17: =COUNTIF(内藤証券!U:U,B17) -> 0
A18: 0D wb | B18: WEB-INF/classes/webbroker3/web/define/RC_ParameterConst.class | C18: ○ | D18: ○ | E18: ファイルが違う | F18: 20250406 新規差分 | N18: 他社展開前 | O18: (46)大和ネクスト銀行でのマイナンバー受入確認義務化に関する追加開発 | Q18: DIS山田 | R18: 45756 | W18: =COUNTIF(内藤証券!U:U,B18) -> 0
A19: 0D wb | B19: WEB-INF/classes/webbroker3/web/define/SessionKeyConst.class | C19: ○ | D19: ○ | E19: ファイルが違う | F19: 20250406 新規差分 | N19: 他社展開前 | O19: (46)大和ネクスト銀行でのマイナンバー受入確認義務化に関する追加開発 | Q19: DIS山田 | R19: 45756 | W19: =COUNTIF(内藤証券!U:U,B19) -> 0
A20: 0D wb | B20: WEB-INF/classes/webbroker3/web/details/accopen/FinancialInstitution.class | C20: ○ | D20: ○ | E20: ファイルが違う | F20: 20250406 新規差分 | N20: 他社展開前 | O20: (46)大和ネクスト銀行でのマイナンバー受入確認義務化に関する追加開発 | Q20: DIS山田 | R20: 45756 | W20: =COUNTIF(内藤証券!U:U,B20) -> 0
A21: 0D wb | B21: WEB-INF/classes/webbroker3/web/details/adminorderexecinq/AdminOREquityOrderExecutionRefUnit.class | C21: ○ | D21: ○ | E21: ファイルが違う | F21: 20250406 新規差分 | N21: 他社展開前 | O21: (44)大引け注文対応 | Q21: DIS山田 | R21: 45756 | W21: =COUNTIF(内藤証券!U:U,B21) -> 0
A22: 0D wb | B22: WEB-INF/classes/webbroker3/web/details/equity/EquityChangeCancelHistoryGroup.class | C22: ○ | D22: ○ | E22: ファイルが違う | F22: 20250406 新規差分 | N22: 他社展開前 | O22: (44)大引け注文対応 | Q22: DIS山田 | R22: 45756 | W22: =COUNTIF(内藤証券!U:U,B22) -> 0
A23: 0D wb | B23: WEB-INF/classes/webbroker3/web/details/equity/EquityExecuteGroup.class | C23: ○ | D23: ○ | E23: ファイルが違う | F23: 20250406 新規差分 | N23: 他社展開前 | O23: (44)大引け注文対応 | Q23: DIS山田 | R23: 45756 | W23: =COUNTIF(内藤証券!U:U,B23) -> 0
A24: 0D wb | B24: WEB-INF/classes/webbroker3/web/details/margin/MarginChangeCancelHistoryGroup.class | C24: ○ | D24: ○ | E24: ファイルが違う | F24: 20250406 新規差分 | N24: 他社展開前 | O24: (44)大引け注文対応 | Q24: DIS山田 | R24: 45756 | W24: =COUNTIF(内藤証券!U:U,B24) -> 0
A25: 0D wb | B25: WEB-INF/classes/webbroker3/web/details/margin/MarginExecuteGroup.class | C25: ○ | D25: ○ | E25: ファイルが違う | F25: 20250406 新規差分 | N25: 他社展開前 | O25: (44)大引け注文対応 | Q25: DIS山田 | R25: 45756 | W25: =COUNTIF(内藤証券!U:U,B25) -> 0
A26: 0D wb | B26: WEB-INF/classes/webbroker3/web/factory/admin/adminorderexecinq/AdminOREquityOrderExecutionDetailsFactory.class | C26: ○ | D26: ○ | E26: ファイルが違う | F26: 20250406 新規差分 | N26: 他社展開前 | O26: (44)大引け注文対応 | Q26: DIS山田 | R26: 45756 | W26: =COUNTIF(内藤証券!U:U,B26) -> 0
... A122: 0D wb | B122: WEB-INF/lib/plug-web3-common.jar | C122: ○ | D122: ○ | E122: ファイルが違う | F122: 20231105 新規差分 | N122: 他社展開前 | O122: (44)大引け注文対応 大和ネクスト銀行でのマイナンバー受入確認義務化に関する追加開発 | Q122: DIS山田 | R122: 45814 | W122: =COUNTIF(内藤証券!U:U,B122) -> 0
A123: 0D wb | B123: WEB-INF/lib/plug-web3-docadmin.jar | C123: ○ | D123: ○ | E123: ファイルが違う | F123: 20250309 新規差分 | N123: METAずれ | Q123: DIS山田 | R123: 45814 | W123: =COUNTIF(内藤証券!U:U,B123) -> 0 | Z123: META
A124: 0D wb | B124: WEB-INF/lib/plug-web3-eqtypeadmin.jar | C124: ○ | D124: ○ | E124: ファイルが違う | F124: 20241103 新規差分 | N124: 他社展開前 | O124: (44)大引け注文対応 | Q124: DIS山田 | R124: 45814 | W124: =COUNTIF(内藤証券!U:U,B124) -> 0
A125: 0D wb | B125: WEB-INF/lib/plug-web3-equity.jar | C125: ○ | D125: ○ | E125: ファイルが違う | F125: 20250406 新規差分 | N125: 他社展開前 | O125: (44)大引け注文対応 | Q125: DIS山田 | R125: 45756 | W125: =COUNTIF(内藤証券!U:U,B125) -> 0
A126: 0D wb | B126: WEB-INF/lib/plug-web3-gentrade.jar | C126: ○ | D126: ○ | E126: ファイルが違う | F126: 20231105 新規差分 | N126: 他社展開前 | O126: (44)大引け注文対応 | Q126: DIS山田 | R126: 45814 | W126: =COUNTIF(内藤証券!U:U,B126) -> 0
A127: 0D wb | B127: WEB-INF/lib/plug-web3-sle-base.jar | C127: ○ | D127: ○ | E127: ファイルが違う | F127: 20210912 新規差分 | G127: 03 | H127: 他社展開前のため | I127: 他社展開で対応。 | J127: 吉澤 | K127: 未定 | N127: 他社展開前 | O127: (0C)外株桁拡張・為替HULFT連携 (46)2021年度カスタマイズ対応 (52)FISエラーメッセージ対応_Ph2 | R127: - | W127: =COUNTIF(内藤証券!U:U,B127) -> 0 | Z127: 古い差分
A128: 0D wb | B128: WEB-INF/lib/plug-web3-sle-gateway.jar | C128: ○ | D128: ○ | E128: ファイルが違う | F128: 20211205 新規差分 | G128: 03 | H128: 他社展開前 | I128: SLE関連のjarのため、市場テスト後にまく | J128: 岡松 | K128: 未定 | N128: 他社展開前 | O128: (52)FISエラーメッセージ対応_Ph1 (52)FISエラーメッセージ対応_Ph2 | R128: - | W128: =COUNTIF(内藤証券!U:U,B128) -> 0 | Z128: 古い差分
A129: 0D wb | B129: WEB-INF/lib/plug-web3-tplib.jar | C129: ○ | D129: ○ | E129: ファイルが違う | F129: 20250406 新規差分 | N129: 他社展開前 | O129: (44)大引け注文対応 | Q129: DIS山田 | R129: 45756 | W129: =COUNTIF(内藤証券!U:U,B129) -> 0
A130: 0D wb | B130: WEB-INF/lib/plug-web3-xbaio.jar | C130: ○ | D130: ○ | E130: ファイルが違う | F130: 20250309 新規差分 | N130: 他社展開前 | O130: 【保守】(46)出金エラー対応 | Q130: DIS山田 | R130: 45814 | W130: =COUNTIF(内藤証券!U:U,B130) -> 0
A131: 0D wb | B131: WEB-INF/src/jp/co/dir/ms/wolf2/LogCryptParamNames.properties | C131: ○ | D131: ○ | E131: ファイルが違う | F131: 20250810 新規差分 | N131: 他社展開前 | O131: パスキー認証レベルアップ対応_要件38 | Q131: DIS山田 | R131: 45883 | W131: =COUNTIF(内藤証券!U:U,B131) -> 0
A132: 0D cw | B132: 0D/pc/aio/WEB3AioCashoutCancelList_inc.jsp | C132: ○ | D132: ○ | E132: ファイルが違う | F132: 20210411 新規差分 | M132: 確認 | N132: コミット漏れ | O132: 3/13実施 (0D)WB4レベルアップ対応 他社展開(0D) 出金取消対応 tar作成 | P132: 黒須代理 | W132: =COUNTIF(内藤証券!U:U,B132) -> 0 | Z132: jsp
A133: 0D cw | B133: WEB-INF/classes/webbroker3/web/beans/application.xml | C133: ○ | D133: ○ | E133: ファイルが違う | F133: 20250105 新規差分 | N133: 他社展開前 | O133: (46)大和ネクスト銀行でのマイナンバー受入確認義務化に関する追加開発 | Q133: DIS山田 | R133: 45814 | W133: =COUNTIF(内藤証券!U:U,B133) -> 0
A134: 0D cw | B134: WEB-INF/classes/webbroker3/web/beans/pc/accinfo/WEB3AccInfoFinancialSearchBean2.class | C134: - | D134: ○ | E134: 本番ファイルがない | F134: 20250406 新規差分 | N134: 他社展開前 | O134: (46)大和ネクスト銀行でのマイナンバー受入確認義務化に関する追加開発 | Q134: DIS山田 | R134: 45756 | W134: =COUNTIF(内藤証券!U:U,B134) -> 0
A135: 0D cw | B135: WEB-INF/classes/webbroker3/web/beans/pc/accinfo/WEB3PcAccInfoMynumberAcceptInfoRegistCompleteBean.class | C135: - | D135: ○ | E135: 本番ファイルがない | F135: 20250406 新規差分 | N135: 他社展開前 | O135: (46)大和ネクスト銀行でのマイナンバー受入確認義務化に関する追加開発 | Q135: DIS山田 | R135: 45756 | W135: =COUNTIF(内藤証券!U:U,B135) -> 0
A136: 0D cw | B136: WEB-INF/classes/webbroker3/web/beans/pc/accinfo/WEB3PcAccInfoMynumberAcceptInfoRegistConfirmBean.class | C136: - | D136: ○ | E136: 本番ファイルがない | F136: 20250406 新規差分 | N136: 他社展開前 | O136: (46)大和ネクスト銀行でのマイナンバー受入確認義務化に関する追加開発 | Q136: DIS山田 | R136: 45756 | W136: =COUNTIF(内藤証券!U:U,B136) -> 0
A137: 0D cw | B137: WEB-INF/classes/webbroker3/web/beans/pc/accinfo/WEB3PcAccInfoMynumberAcceptInfoRegistInputBean.class | C137: - | D137: ○ | E137: 本番ファイルがない | F137: 20250406 新規差分 | N137: 他社展開前 | O137: (46)大和ネクスト銀行でのマイナンバー受入確認義務化に関する追加開発 | Q137: DIS山田 | R137: 45756 | W137: =COUNTIF(内藤証券!U:U,B137) -> 0
A138: 0D cw | B138: WEB-INF/classes/webbroker3/web/beans/rc/login/WEB3RcLoginAuthCodeConfirmInputBean.class | C138: - | D138: ○ | E138: 本番ファイルがない | F138: 20250810 新規差分 | N138: 他社展開前 | O138: ログイン時多要素認証の導入_API対応 | Q138: DIS山田 | R138: 45883 | W138: =COUNTIF(内藤証券!U:U,B138) -> 0
A139: 0D cw | B139: WEB-INF/classes/webbroker3/web/define/AD_OR_ParameterConst.class | C139: ○ | D139: ○ | E139: ファイルが違う | F139: 20250406 新規差分 | N139: 他社展開前 | O139: (44)大引け注文対応 | Q139: DIS山田 | R139: 45756 | W139: =COUNTIF(内藤証券!U:U,B139) -> 0
A140: 0D cw | B140: WEB-INF/classes/webbroker3/web/define/AI_ParameterConst.class | C140: ○ | D140: ○ | E140: ファイルが違う | F140: 20250209 新規差分 | N140: 他社展開前 | O140: (46)大和ネクスト銀行でのマイナンバー受入確認義務化に関する追加開発 | Q140: DIS山田 | R140: 45814 | W140: =COUNTIF(内藤証券!U:U,B140) -> 0
A141: 0D cw | B141: WEB-INF/classes/webbroker3/web/define/CodeValueConst.class | C141: ○ | D141: ○ | E141: ファイルが違う | F141: 20250209 新規差分 | N141: 他社展開前 | O141: (46)大和ネクスト銀行でのマイナンバー受入確認義務化に関する追加開発 (44)大引け注文対応 | Q141: DIS山田 | R141: 45814 | W141: =COUNTIF(内藤証券!U:U,B141) -> 1 | Z141: CodeValueConst.class 記載重複
A142: 0D cw | B142: WEB-INF/classes/webbroker3/web/define/EQ_ParameterConst.class | C142: ○ | D142: ○ | E142: ファイルが違う | F142: 20250406 新規差分 | N142: 他社展開前 | O142: (44)大引け注文対応 | Q142: DIS山田 | R142: 45756 | W142: =COUNTIF(内藤証券!U:U,B142) -> 0
A143: 0D cw | B143: WEB-INF/classes/webbroker3/web/define/MF_ParameterConst.class | C143: ○ | D143: ○ | E143: ファイルが違う | F143: 20250810 新規差分 | N143: 他社展開前 | O143: (0F)投資信託銘柄検索機能の追加 | Q143: DIS山田 | R143: 45883 | W143: =COUNTIF(内藤証券!U:U,B143) -> 0
A144: 0D cw | B144: WEB-INF/classes/webbroker3/web/define/MR_ParameterConst.class | C144: ○ | D144: ○ | E144: ファイルが違う | F144: 20250406 新規差分 | N144: 他社展開前 | O144: (44)大引け注文対応 | Q144: DIS山田 | R144: 45756 | W144: =COUNTIF(内藤証券!U:U,B144) -> 0
A145: 0D cw | B145: WEB-INF/classes/webbroker3/web/define/RC_ParameterConst.class | C145: ○ | D145: ○ | E145: ファイルが違う | F145: 20250406 新規差分 | N145: 他社展開前 | O145: (46)大和ネクスト銀行でのマイナンバー受入確認義務化に関する追加開発 | Q145: DIS山田 | R145: 45756 | W145: =COUNTIF(内藤証券!U:U,B145) -> 0
A146: 0D cw | B146: WEB-INF/classes/webbroker3/web/define/SessionKeyConst.class | C146: ○ | D146: ○ | E146: ファイルが違う | F146: 20250406 新規差分 | N146: 他社展開前 | O146: (46)大和ネクスト銀行でのマイナンバー受入確認義務化に関する追加開発 | Q146: DIS山田 | R146: 45756 | W146: =COUNTIF(内藤証券!U:U,B146) -> 0
A147: 0D cw | B147: WEB-INF/classes/webbroker3/web/details/accopen/FinancialInstitution.class | C147: ○ | D147: ○ | E147: ファイルが違う | F147: 20250406 新規差分 | N147: 他社展開前 | O147: (46)大和ネクスト銀行でのマイナンバー受入確認義務化に関する追加開発 | Q147: DIS山田 | R147: 45756 | W147: =COUNTIF(内藤証券!U:U,B147) -> 0
A148: 0D cw | B148: WEB-INF/classes/webbroker3/web/details/adminorderexecinq/AdminOREquityOrderExecutionRefUnit.class | C148: ○ | D148: ○ | E148: ファイルが違う | F148: 20250406 新規差分 | N148: 他社展開前 | O148: (44)大引け注文対応 | Q148: DIS山田 | R148: 45756 | W148: =COUNTIF(内藤証券!U:U,B148) -> 0
A149: 0D cw | B149: WEB-INF/classes/webbroker3/web/details/equity/EquityChangeCancelHistoryGroup.class | C149: ○ | D149: ○ | E149: ファイルが違う | F149: 20250406 新規差分 | N149: 他社展開前 | O149: (44)大引け注文対応 | Q149: DIS山田 | R149: 45756 | W149: =COUNTIF(内藤証券!U:U,B149) -> 0
A150: 0D cw | B150: WEB-INF/classes/webbroker3/web/details/equity/EquityExecuteGroup.class | C150: ○ | D150: ○ | E150: ファイルが違う | F150: 20250406 新規差分 | N150: 他社展開前 | O150: (44)大引け注文対応 | Q150: DIS山田 | R150: 45756 | W150: =COUNTIF(内藤証券!U:U,B150) -> 0
A151: 0D cw | B151: WEB-INF/classes/webbroker3/web/details/margin/MarginChangeCancelHistoryGroup.class | C151: ○ | D151: ○ | E151: ファイルが違う | F151: 20250406 新規差分 | N151: 他社展開前 | O151: (44)大引け注文対応 | Q151: DIS山田 | R151: 45756 | W151: =COUNTIF(内藤証券!U:U,B151) -> 0
A152: 0D cw | B152: WEB-INF/classes/webbroker3/web/details/margin/MarginExecuteGroup.class | C152: ○ | D152: ○ | E152: ファイルが違う | F152: 20250406 新規差分 | N152: 他社展開前 | O152: (44)大引け注文対応 | Q152: DIS山田 | R152: 45756 | W152: =COUNTIF(内藤証券!U:U,B152) -> 0
A153: 0D cw | B153: WEB-INF/classes/webbroker3/web/factory/admin/adminorderexecinq/AdminOREquityOrderExecutionDetailsFactory.class | C153: ○ | D153: ○ | E153: ファイルが違う | F153: 20250406 新規差分 | N153: 他社展開前 | O153: (44)大引け注文対応 | Q153: DIS山田 | R153: 45756 | W153: =COUNTIF(内藤証券!U:U,B153) -> 0
... A249: 0D cw | B249: WEB-INF/lib/plug-web3-common.jar | C249: ○ | D249: ○ | E249: ファイルが違う | F249: 20231105 新規差分 | N249: 他社展開前 | O249: (44)大引け注文対応 大和ネクスト銀行でのマイナンバー受入確認義務化に関する追加開発 | Q249: DIS山田 | R249: 45814 | W249: =COUNTIF(内藤証券!U:U,B249) -> 0
A250: 0D cw | B250: WEB-INF/lib/plug-web3-docadmin.jar | C250: ○ | D250: ○ | E250: ファイルが違う | F250: 20250309 新規差分 | N250: METAずれ | Q250: DIS山田 | R250: 45814 | W250: =COUNTIF(内藤証券!U:U,B250) -> 0 | Z250: =A250&" "&B250 -> 0D cw WEB-INF/lib/plug-web3-docadmin.jar
A251: 0D cw | B251: WEB-INF/lib/plug-web3-eqtypeadmin.jar | C251: ○ | D251: ○ | E251: ファイルが違う | F251: 20241103 新規差分 | N251: 他社展開前 | O251: (44)大引け注文対応 | Q251: DIS山田 | R251: 45814 | W251: =COUNTIF(内藤証券!U:U,B251) -> 0
A252: 0D cw | B252: WEB-INF/lib/plug-web3-equity.jar | C252: ○ | D252: ○ | E252: ファイルが違う | F252: 20250406 新規差分 | N252: 他社展開前 | O252: (44)大引け注文対応 | Q252: DIS山田 | R252: 45756 | W252: =COUNTIF(内藤証券!U:U,B252) -> 0
A253: 0D cw | B253: WEB-INF/lib/plug-web3-gentrade.jar | C253: ○ | D253: ○ | E253: ファイルが違う | F253: 20231105 新規差分 | N253: 他社展開前 | O253: (44)大引け注文対応 | Q253: DIS山田 | R253: 45814 | W253: =COUNTIF(内藤証券!U:U,B253) -> 0
A254: 0D cw | B254: WEB-INF/lib/plug-web3-sle-base.jar | C254: ○ | D254: ○ | E254: ファイルが違う | F254: 20210912 新規差分 | G254: 03 | H254: 他社展開前のため | I254: 他社展開で対応。 | J254: 吉澤 | K254: 未定 | N254: 他社展開前 | O254: (0C)外株桁拡張・為替HULFT連携 (46)2021年度カスタマイズ対応 (52)FISエラーメッセージ対応_Ph2 | R254: - | W254: =COUNTIF(内藤証券!U:U,B254) -> 0 | Z254: 古い差分
A255: 0D cw | B255: WEB-INF/lib/plug-web3-sle-gateway.jar | C255: ○ | D255: ○ | E255: ファイルが違う | F255: 20211205 新規差分 | G255: 03 | H255: 他社展開前 | I255: SLE関連のjarのため、市場テスト後にまく | J255: 岡松 | K255: 未定 | N255: 他社展開前 | O255: (52)FISエラーメッセージ対応_Ph1 (52)FISエラーメッセージ対応_Ph2 | R255: - | W255: =COUNTIF(内藤証券!U:U,B255) -> 0 | Z255: 古い差分
A256: 0D cw | B256: WEB-INF/lib/plug-web3-tplib.jar | C256: ○ | D256: ○ | E256: ファイルが違う | F256: 20250406 新規差分 | N256: 他社展開前 | O256: (44)大引け注文対応 | Q256: DIS山田 | R256: 45756 | W256: =COUNTIF(内藤証券!U:U,B256) -> 0
A257: 0D cw | B257: WEB-INF/lib/plug-web3-xbaio.jar | C257: ○ | D257: ○ | E257: ファイルが違う | F257: 20250309 新規差分 | N257: 他社展開前 | O257: 【保守】(46)出金エラー対応 | Q257: DIS山田 | R257: 45814 | W257: =COUNTIF(内藤証券!U:U,B257) -> 0
A258: 0D cw | B258: WEB-INF/src/jp/co/dir/ms/wolf2/LogCryptParamNames.properties | C258: ○ | D258: ○ | E258: ファイルが違う | F258: 20250810 新規差分 | N258: 他社展開前 | O258: パスキー認証レベルアップ対応_要件38 | Q258: DIS山田 | R258: 45883 | W258: =COUNTIF(内藤証券!U:U,B258) -> 0
A259: 08 wb | B259: 08/pc/WEB3AccountLogin_close.jsp | C259: - | D259: ○ | E259: 本番ファイルがない | F259: 20210411 新規差分 | G259: 90 | H259: 2021/6/2 関谷 概要欄に記載の通り、チェック不要としてよいのではないでしょうか？ | I259: - | J259: - | K259: - | L259: - | N259: [OS更改前除外対象]cwには本番あり、cw本番削除？ （新サイトの本番実施によるサービス停止を行った、システムメンテナンス時のみ、使用する。バックアップサイトのログイン画面を閉じる内容だが、 UPDATEする際はWEB3AccountLogin.jspにリネームして使用する[杉岡]） | O259: 金融OS更改 | R259: - | W259: =COUNTIF(内藤証券!U:U,B259) -> 0 | Z259: 撤退：フィデリティ
A260: 08 wb | B260: 08/pc/WEB3AccountLogin_open.jsp | C260: - | D260: ○ | E260: 本番ファイルがない | F260: 20210411 新規差分 | G260: 90 | H260: 2021/6/2 関谷 概要欄に記載の通り、チェック不要としてよいのではないでしょうか？ | I260: - | J260: - | K260: - | L260: - | N260: [OS更改前除外対象]cwには本番あり、cw本番削除？ （新サイトの本番実施によるサービス停止を行った、システムメンテナンス時のみ、使用する。バックアップサイトのログイン画面を閉じる内容だが、 UPDATEする際はWEB3AccountLogin.jspにリネームして使用する[杉岡]） | O260: 金融OS更改 | R260: - | W260: =COUNTIF(内藤証券!U:U,B260) -> 0 | Z260: 撤退：フィデリティ
A261: 08 wb | B261: WEB-INF/classes/InputCheckPropertyFileMap.properties | C261: ○ | D261: ○ | E261: ファイルが違う | F261: 20250209 新規差分 | N261: 他社展開前 | O261: (09)対面顧客向けネット環境の導入 | Q261: 小林（由） | R261: 45756 | W261: =COUNTIF(内藤証券!U:U,B261) -> 0 | Z261: 撤退：フィデリティ
A262: 08 wb | B262: WEB-INF/classes/ssoConnection52.properties | C262: ○ | D262: - | E262: SVNファイルがない | F262: 20210411 新規差分 | G262: 90 | H262: 2021/6/2 関谷 不要資源 | I262: 本番から削除する | J262: 関谷 | N262: 本番削除 実施対象外資源として、PGMでSVN取得対象から除外 本番に存在するのは wb308wb/cw wb30hwb/cw wb352wb/cw で、同じ共同1のwb447wb/cw には存在しない、他環境の本番にも存在しない | O262: 金融OS更改 | R262: - | W262: =COUNTIF(内藤証券!U:U,B262) -> 0 | Z262: 撤退：フィデリティ
A263: 08 wb | B263: WEB-INF/classes/webbroker3/web/beans/admin/eqtypeadmin/WEB3AdminPMFailureOrderDownloadBean.class | C263: - | D263: ○ | E263: 本番ファイルがない | F263: 20241103 新規差分 | N263: 他社展開前 | O263: (全社)発注エンジン統合 | Q263: 小林（由） | R263: 45756 | W263: =COUNTIF(内藤証券!U:U,B263) -> 0 | Z263: 撤退：フィデリティ
A264: 08 wb | B264: WEB-INF/classes/webbroker3/web/beans/admin/eqtypeadmin/WEB3AdminPMFailureOrderDownloadInputBean.class | C264: - | D264: ○ | E264: 本番ファイルがない | F264: 20241103 新規差分 | N264: 他社展開前 | O264: (全社)発注エンジン統合 | Q264: 小林（由） | R264: 45756 | W264: =COUNTIF(内藤証券!U:U,B264) -> 0 | Z264: 撤退：フィデリティ
A265: 08 wb | B265: WEB-INF/classes/webbroker3/web/beans/application.xml | C265: ○ | D265: ○ | E265: ファイルが違う | F265: 20240707 新規差分 | N265: 他社展開前 | O265: (46)大和ネクスト銀行でのマイナンバー受入確認義務化に関する追加開発 | Q265: DIS山田 | R265: 45814 | W265: =COUNTIF(内藤証券!U:U,B265) -> 0
A266: 08 wb | B266: WEB-INF/classes/webbroker3/web/beans/login/WEB3FPTRegistBean.class | C266: - | D266: ○ | E266: 本番ファイルがない | F266: 20250209 新規差分 | N266: 他社展開前 | O266: (09)対面顧客向けネット環境の導入 (09)対面顧客向けネット環境の導入_金商法交付データ連携不具合対応 | Q266: 小林（由） | R266: 45756 | W266: =COUNTIF(内藤証券!U:U,B266) -> 0 | Z266: 撤退：フィデリティ
A267: 08 wb | B267: WEB-INF/classes/webbroker3/web/beans/pc/accinfo/WEB3AccInfoFinancialSearchBean2.class | C267: - | D267: ○ | E267: 本番ファイルがない | F267: 20250406 新規差分 | N267: 他社展開前 | O267: (46)大和ネクスト銀行でのマイナンバー受入確認義務化に関する追加開発 | Q267: DIS山田 | R267: 45756 | W267: =COUNTIF(内藤証券!U:U,B267) -> 0
A268: 08 wb | B268: WEB-INF/classes/webbroker3/web/beans/pc/accinfo/WEB3PcAccInfoMynumberAcceptInfoRegistCompleteBean.class | C268: - | D268: ○ | E268: 本番ファイルがない | F268: 20250406 新規差分 | N268: 他社展開前 | O268: (46)大和ネクスト銀行でのマイナンバー受入確認義務化に関する追加開発 | Q268: DIS山田 | R268: 45756 | W268: =COUNTIF(内藤証券!U:U,B268) -> 0
A269: 08 wb | B269: WEB-INF/classes/webbroker3/web/beans/pc/accinfo/WEB3PcAccInfoMynumberAcceptInfoRegistConfirmBean.class | C269: - | D269: ○ | E269: 本番ファイルがない | F269: 20250406 新規差分 | N269: 他社展開前 | O269: (46)大和ネクスト銀行でのマイナンバー受入確認義務化に関する追加開発 | Q269: DIS山田 | R269: 45756 | W269: =COUNTIF(内藤証券!U:U,B269) -> 0
A270: 08 wb | B270: WEB-INF/classes/webbroker3/web/beans/pc/accinfo/WEB3PcAccInfoMynumberAcceptInfoRegistInputBean.class | C270: - | D270: ○ | E270: 本番ファイルがない | F270: 20250406 新規差分 | N270: 他社展開前 | O270: (46)大和ネクスト銀行でのマイナンバー受入確認義務化に関する追加開発 | Q270: DIS山田 | R270: 45756 | W270: =COUNTIF(内藤証券!U:U,B270) -> 0
A271: 08 wb | B271: WEB-INF/classes/webbroker3/web/beans/pc/gentrade/WEB3PcPostInfoDisplayBean2.class | C271: - | D271: ○ | E271: 本番ファイルがない | F271: 20250105 新規差分 | N271: 他社展開前 | O271: (0G)Plateシステム対応_投資案件_12月実施 | Q271: 小林（由） | R271: 45756 | W271: =COUNTIF(内藤証券!U:U,B271) -> 0 | Z271: 撤退：フィデリティ
A272: 08 wb | B272: WEB-INF/classes/webbroker3/web/beans/pc/mutual/WEB3PcMutualAcmltChangeApplyCompleteBean.class | C272: ○ | D272: ○ | E272: ファイルが違う | F272: 20250105 新規差分 | N272: 他社展開前 | O272: (0G)Plateシステム対応_投資案件_12月実施 | Q272: 小林（由） | R272: 45756 | W272: =COUNTIF(内藤証券!U:U,B272) -> 0 | Z272: 撤退：フィデリティ
A273: 08 wb | B273: WEB-INF/classes/webbroker3/web/beans/pc/mutual/WEB3PcMutualAcmltNewApplyCompleteBean.class | C273: ○ | D273: ○ | E273: ファイルが違う | F273: 20250105 新規差分 | N273: 他社展開前 | O273: (0G)Plateシステム対応_投資案件_12月実施 | Q273: 小林（由） | R273: 45756 | W273: =COUNTIF(内藤証券!U:U,B273) -> 0 | Z273: 撤退：フィデリティ
A274: 08 wb | B274: WEB-INF/classes/webbroker3/web/beans/pc/mutual/WEB3PcMutualApplyCompleteBean.class | C274: ○ | D274: ○ | E274: ファイルが違う | F274: 20250105 新規差分 | N274: 他社展開前 | O274: (0G)Plateシステム対応_投資案件_12月実施 | Q274: 小林（由） | R274: 45756 | W274: =COUNTIF(内藤証券!U:U,B274) -> 0 | Z274: 撤退：フィデリティ
A275: 08 wb | B275: WEB-INF/classes/webbroker3/web/beans/pc/mutual/WEB3PcMutualBuyCompleteBean.class | C275: ○ | D275: ○ | E275: ファイルが違う | F275: 20250105 新規差分 | N275: 他社展開前 | O275: (0G)Plateシステム対応_投資案件_12月実施 | Q275: 小林（由） | R275: 45756 | W275: =COUNTIF(内藤証券!U:U,B275) -> 0 | Z275: 撤退：フィデリティ
A276: 08 wb | B276: WEB-INF/classes/webbroker3/web/beans/pc/mutual/WEB3PcMutualSellCompleteBean.class | C276: ○ | D276: ○ | E276: ファイルが違う | F276: 20250105 新規差分 | N276: 他社展開前 | O276: (0G)Plateシステム対応_投資案件_12月実施 | Q276: 小林（由） | R276: 45756 | W276: =COUNTIF(内藤証券!U:U,B276) -> 0 | Z276: 撤退：フィデリティ
A277: 08 wb | B277: WEB-INF/classes/webbroker3/web/beans/rc/login/WEB3RcLoginAuthCodeConfirmInputBean.class | C277: - | D277: ○ | E277: 本番ファイルがない | F277: 20250810 新規差分 | N277: 他社展開前 | O277: ログイン時多要素認証の導入_API対応 | Q277: DIS山田 | R277: 45883 | W277: =COUNTIF(内藤証券!U:U,B277) -> 0 | Z277: 撤退：フィデリティ
A278: 08 wb | B278: WEB-INF/classes/webbroker3/web/define/AA_CodeValueConst.class | C278: ○ | D278: ○ | E278: ファイルが違う | F278: 20250209 新規差分 | N278: 他社展開前 | O278: (09)対面顧客向けネット環境の導入 | Q278: 小林（由） | R278: 45756 | W278: =COUNTIF(内藤証券!U:U,B278) -> 0 | Z278: 撤退：フィデリティ
A279: 08 wb | B279: WEB-INF/classes/webbroker3/web/define/AA_JSPFileNameConst.class | C279: ○ | D279: ○ | E279: ファイルが違う | F279: 20250706 新規差分 | N279: 他社展開前 | O279: ログイン時多要素認証の導入_脆弱性対応 | Q279: DIS山田 | R279: 45847 | W279: =COUNTIF(内藤証券!U:U,B279) -> 1 | Z279: 撤退：フィデリティ
A280: 08 wb | B280: WEB-INF/classes/webbroker3/web/define/AA_ParameterConst.class | C280: ○ | D280: ○ | E280: ファイルが違う | F280: 20250105 新規差分 | N280: 他社展開前 | O280: (0G)Plateシステム対応_投資案件_12月実施 (09)対面顧客向けネット環境の導入 (09)対面顧客向けネット環境の導入_追加対応 | Q280: 小林（由） | R280: 45756 | W280: =COUNTIF(内藤証券!U:U,B280) -> 0 | Z280: 撤退：フィデリティ
A281: 08 wb | B281: WEB-INF/classes/webbroker3/web/define/AD_OR_ParameterConst.class | C281: ○ | D281: ○ | E281: ファイルが違う | F281: 20250406 新規差分 | N281: 他社展開前 | O281: (44)大引け注文対応 | Q281: DIS山田 | R281: 45756 | W281: =COUNTIF(内藤証券!U:U,B281) -> 0
A282: 08 wb | B282: WEB-INF/classes/webbroker3/web/define/AI_ParameterConst.class | C282: ○ | D282: ○ | E282: ファイルが違う | F282: 20240804 新規差分 | N282: 他社展開前 | O282: (46)大和ネクスト銀行でのマイナンバー受入確認義務化に関する追加開発 | Q282: DIS山田 | R282: 45814 | W282: =COUNTIF(内藤証券!U:U,B282) -> 0
A283: 08 wb | B283: WEB-INF/classes/webbroker3/web/define/BD_ParameterConst.class | C283: ○ | D283: ○ | E283: ファイルが違う | F283: 20250209 新規差分 | N283: 他社展開前 | O283: (09)対面顧客向けネット環境の導入 | Q283: 小林（由） | R283: 45756 | W283: =COUNTIF(内藤証券!U:U,B283) -> 0 | Z283: 撤退：フィデリティ
A284: 08 wb | B284: WEB-INF/classes/webbroker3/web/define/CodeValueConst.class | C284: ○ | D284: ○ | E284: ファイルが違う | F284: 20250209 新規差分 | N284: 他社展開前 | O284: (46)大和ネクスト銀行でのマイナンバー受入確認義務化に関する追加開発 (44)大引け注文対応 | Q284: DIS山田 | R284: 45814 | W284: =COUNTIF(内藤証券!U:U,B284) -> 1 | Z284: CodeValueConst.class 記載重複
A285: 08 wb | B285: WEB-INF/classes/webbroker3/web/define/EQ_ParameterConst.class | C285: ○ | D285: ○ | E285: ファイルが違う | F285: 20250406 新規差分 | N285: 他社展開前 | O285: (44)大引け注文対応 | Q285: DIS山田 | R285: 45756 | W285: =COUNTIF(内藤証券!U:U,B285) -> 0
A286: 08 wb | B286: WEB-INF/classes/webbroker3/web/define/LG_ParameterConst.class | C286: ○ | D286: ○ | E286: ファイルが違う | F286: 20250209 新規差分 | N286: 他社展開前 | O286: (09)対面顧客向けネット環境の導入 | Q286: 小林（由） | R286: 45756 | W286: =COUNTIF(内藤証券!U:U,B286) -> 0 | Z286: 撤退：フィデリティ
A287: 08 wb | B287: WEB-INF/classes/webbroker3/web/define/MF_ParameterConst.class | C287: ○ | D287: ○ | E287: ファイルが違う | F287: 20250209 新規差分 | N287: 他社展開前 | O287: (09)対面顧客向けネット環境の導入 | Q287: 小林（由） | R287: 45756 | W287: =COUNTIF(内藤証券!U:U,B287) -> 0
A288: 08 wb | B288: WEB-INF/classes/webbroker3/web/define/MR_ParameterConst.class | C288: ○ | D288: ○ | E288: ファイルが違う | F288: 20250406 新規差分 | N288: 他社展開前 | O288: (44)大引け注文対応 | Q288: DIS山田 | R288: 45756 | W288: =COUNTIF(内藤証券!U:U,B288) -> 0
A289: 08 wb | B289: WEB-INF/classes/webbroker3/web/define/RC_ParameterConst.class | C289: ○ | D289: ○ | E289: ファイルが違う | F289: 20250406 新規差分 | N289: 他社展開前 | O289: (46)大和ネクスト銀行でのマイナンバー受入確認義務化に関する追加開発 | Q289: DIS山田 | R289: 45756 | W289: =COUNTIF(内藤証券!U:U,B289) -> 0
A290: 08 wb | B290: WEB-INF/classes/webbroker3/web/define/SessionKeyConst.class | C290: ○ | D290: ○ | E290: ファイルが違う | F290: 20250406 新規差分 | N290: 他社展開前 | O290: (46)大和ネクスト銀行でのマイナンバー受入確認義務化に関する追加開発 | Q290: DIS山田 | R290: 45756 | W290: =COUNTIF(内藤証券!U:U,B290) -> 0
...

Sheet 内藤証券
A1: モジュール情報 | K1: 配信 | L1: 同期 | M1: SVN | N1: 移行フェーズ | R1: 参考
A2: No | B2: サーバー | C2: ディレクトリ | E2: File名 | F2: Size | G2: TimeStamp | H2: 機能名 | I2: 修正 区分 | J2: ＵＰ区分 | K2: 環境 | M2: リビジョン | N2: UP予定日 | O2: UP区分 | P2: UP担当者 | Q2: ユーザID | R2: 変更概要（※案件名を記入） | S2: 備考（※定型案件の場合「定型案件」と記入） | X2: memo
A3: 1 | B3: PR層 | C3: /wb[cw]/wb[cw]_stage/ | D3: ./webbroker3.war/WEB-INF/classes/webbroker3/web/beans/pc/accinfo/ | E3: WEB3PcAccInfoMfaPskRegistCompleteBean.class | F3: 2062 | G3: 46211.782 | H3: ■PB00202136_44パスキー未登録顧客のSSO不可対応 | I3: 変更 | J3: 通常 | K3: 0D | L3: [ap][wb] | U3: =SUBSTITUTE(SUBSTITUTE(D3&"/"&E3,"//","/"),"./webbroker3.war/",) -> WEB-INF/classes/webbroker3/web/beans/pc/accinfo/WEB3PcAccInfoMfaPskRegistCompleteBean.class | V3: =COUNTIF(wb4_20250810_pr!B$4:B$258,U3) -> 0
A4: 2 | B4: PR層 | C4: /wb[cw]/wb[cw]_stage/ | D4: ./webbroker3.war/WEB-INF/classes/webbroker3/web/define/ | E4: CodeValueConst.class | F4: 117586 | G4: 46211.782 | H4: ■PB00202136_44パスキー未登録顧客のSSO不可対応 | I4: 変更 | J4: 通常 | K4: 0D | L4: [ap][wb] | U4: =SUBSTITUTE(SUBSTITUTE(D4&"/"&E4,"//","/"),"./webbroker3.war/",) -> WEB-INF/classes/webbroker3/web/define/CodeValueConst.class | V4: =COUNTIF(wb4_20250810_pr!B$4:B$258,U4) -> 2
A5: 3 | B5: PR層 | C5: /wb[cw]/wb[cw]_stage/ | D5: ./webbroker3.war/WEB-INF/classes/webbroker3/web/beans/ | E5: WEB3XTradeSessionUpdate0FEqBean.class | F5: 1562 | G5: 45937.653 | H5: ■PB00201704_0FQUICK連携対応 | I5: 変更 | J5: 通常 | K5: 0D | L5: [ap][wb] | U5: =SUBSTITUTE(SUBSTITUTE(D5&"/"&E5,"//","/"),"./webbroker3.war/",) -> WEB-INF/classes/webbroker3/web/beans/WEB3XTradeSessionUpdate0FEqBean.class | V5: =COUNTIF(wb4_20250810_pr!B$4:B$258,U5) -> 0
A6: 4 | B6: PR層 | C6: /wb[cw]/wb[cw]_stage/ | D6: ./webbroker3.war/WEB-INF/classes/webbroker3/web/define/ | E6: AA_JSPFileNameConst.class | F6: 3311 | G6: 45937.653 | H6: ■PB00201704_0FQUICK連携対応 | I6: 変更 | J6: 通常 | K6: 0D | L6: [ap][wb] | U6: =SUBSTITUTE(SUBSTITUTE(D6&"/"&E6,"//","/"),"./webbroker3.war/",) -> WEB-INF/classes/webbroker3/web/define/AA_JSPFileNameConst.class | V6: =COUNTIF(wb4_20250810_pr!B$4:B$258,U6) -> 0
A7: 5 | B7: PR層 | C7: /wb[cw]/wb[cw]_stage/ | D7: ./webbroker3.war/WEB-INF/src/webbroker3/web/beans/ | E7: application.xml | F7: 778230 | G7: 45937.653 | H7: ■PB00201704_0FQUICK連携対応 | I7: 変更 | J7: 通常 | K7: 0D | L7: [ap][wb] | U7: =SUBSTITUTE(SUBSTITUTE(D7&"/"&E7,"//","/"),"./webbroker3.war/",) -> WEB-INF/src/webbroker3/web/beans/application.xml | V7: =COUNTIF(wb4_20250810_pr!B$4:B$258,U7) -> 0

Sheet 対面共同
A1: モジュール情報 | K1: 配信 | L1: 同期 | M1: SVN | N1: 移行フェーズ | R1: 参考
A2: No | B2: サーバー | C2: ディレクトリ | E2: File名 | F2: Size | G2: TimeStamp | H2: 機能名 | I2: 修正 区分 | J2: ＵＰ区分 | K2: 環境 | M2: リビジョン | N2: UP予定日 | O2: UP区分 | P2: UP担当者 | Q2: ユーザID | R2: 変更概要（※案件名を記入） | S2: 備考（※定型案件の場合「定型案件」と記入） | X2: memo
A3: 1 | B3: PR層 | C3: /wb[cw]/wb[cw]_stage/ | D3: ./webbroker3.war/WEB-INF/classes/webbroker3/web/beans/pc/accinfo/ | E3: WEB3PcAccInfoMfaPskRegistCompleteBean.class | F3: 2062 | G3: 46211.782 | H3: ■PB00202136_44パスキー未登録顧客のSSO不可対応 | I3: 変更 | J3: 通常 | K3: P0 | L3: [ap][wb] | U3: =SUBSTITUTE(SUBSTITUTE(D3&"/"&E3,"//","/"),"./webbroker3.war/",) -> WEB-INF/classes/webbroker3/web/beans/pc/accinfo/WEB3PcAccInfoMfaPskRegistCompleteBean.class | V3: =COUNTIF(wb4_20250810_pr!B$621:B$757,U3) -> 0
A4: 2 | B4: PR層 | C4: /wb[cw]/wb[cw]_stage/ | D4: ./webbroker3.war/WEB-INF/classes/webbroker3/web/define/ | E4: CodeValueConst.class | F4: 117586 | G4: 46211.782 | H4: ■PB00202136_44パスキー未登録顧客のSSO不可対応 | I4: 変更 | J4: 通常 | K4: P0 | L4: [ap][wb] | U4: =SUBSTITUTE(SUBSTITUTE(D4&"/"&E4,"//","/"),"./webbroker3.war/",) -> WEB-INF/classes/webbroker3/web/define/CodeValueConst.class | V4: =COUNTIF(wb4_20250810_pr!B$621:B$757,U4) -> 1
A5: 3 | B5: PR層 | C5: /wb[cw]/wb[cw]_stage/ | D5: ./webbroker3.war/WEB-INF/classes/webbroker3/web/beans/ | E5: WEB3XTradeSessionUpdate0FEqBean.class | F5: 1562 | G5: 45937.653 | H5: ■PB00201704_0FQUICK連携対応 | I5: 変更 | J5: 通常 | K5: P0 | L5: [ap][wb] | U5: =SUBSTITUTE(SUBSTITUTE(D5&"/"&E5,"//","/"),"./webbroker3.war/",) -> WEB-INF/classes/webbroker3/web/beans/WEB3XTradeSessionUpdate0FEqBean.class | V5: =COUNTIF(wb4_20250810_pr!B$621:B$757,U5) -> 0
A6: 4 | B6: PR層 | C6: /wb[cw]/wb[cw]_stage/ | D6: ./webbroker3.war/WEB-INF/classes/webbroker3/web/define/ | E6: AA_JSPFileNameConst.class | F6: 3311 | G6: 45937.653 | H6: ■PB00201704_0FQUICK連携対応 | I6: 変更 | J6: 通常 | K6: P0 | L6: [ap][wb] | U6: =SUBSTITUTE(SUBSTITUTE(D6&"/"&E6,"//","/"),"./webbroker3.war/",) -> WEB-INF/classes/webbroker3/web/define/AA_JSPFileNameConst.class | V6: =COUNTIF(wb4_20250810_pr!B$621:B$757,U6) -> 1
A7: 5 | B7: PR層 | C7: /wb[cw]/wb[cw]_stage/ | D7: ./webbroker3.war/WEB-INF/src/webbroker3/web/beans/ | E7: application.xml | F7: 778230 | G7: 45937.653 | H7: ■PB00201704_0FQUICK連携対応 | I7: 変更 | J7: 通常 | K7: P0 | L7: [ap][wb] | U7: =SUBSTITUTE(SUBSTITUTE(D7&"/"&E7,"//","/"),"./webbroker3.war/",) -> WEB-INF/src/webbroker3/web/beans/application.xml | V7: =COUNTIF(wb4_20250810_pr!B$621:B$757,U7) -> 0

Sheet スマートプラス
A1: モジュール情報 | K1: 配信 | L1: 同期 | M1: SVN | N1: 移行フェーズ | R1: 参考
A2: No | B2: サーバー | C2: ディレクトリ | E2: File名 | F2: Size | G2: TimeStamp | H2: 機能名 | I2: 修正 区分 | J2: ＵＰ区分 | K2: 環境 | M2: リビジョン | N2: UP予定日 | O2: UP区分 | P2: UP担当者 | Q2: ユーザID | R2: 変更概要（※案件名を記入） | S2: 備考（※定型案件の場合「定型案件」と記入） | X2: memo
A3: 1 | B3: PR層 | C3: /wb[cw]/wb[cw]_stage/ | D3: ./webbroker3.war/WEB-INF/classes/webbroker3/web/beans/pc/accinfo/ | E3: WEB3PcAccInfoMfaPskRegistCompleteBean.class | F3: 2062 | G3: 46211.782 | H3: ■PB00202136_44パスキー未登録顧客のSSO不可対応 | I3: 変更 | J3: 通常 | K3: 0C | L3: [ap][wb] | U3: =SUBSTITUTE(SUBSTITUTE(D3&"/"&E3,"//","/"),"./webbroker3.war/",) -> WEB-INF/classes/webbroker3/web/beans/pc/accinfo/WEB3PcAccInfoMfaPskRegistCompleteBean.class | V3: =COUNTIF(wb4_20250810_pr!B$1122:B$1395,U3) -> 0
A4: 2 | B4: PR層 | C4: /wb[cw]/wb[cw]_stage/ | D4: ./webbroker3.war/WEB-INF/classes/webbroker3/web/define/ | E4: CodeValueConst.class | F4: 117586 | G4: 46211.782 | H4: ■PB00202136_44パスキー未登録顧客のSSO不可対応 | I4: 変更 | J4: 通常 | K4: 0C | L4: [ap][wb] | U4: =SUBSTITUTE(SUBSTITUTE(D4&"/"&E4,"//","/"),"./webbroker3.war/",) -> WEB-INF/classes/webbroker3/web/define/CodeValueConst.class | V4: =COUNTIF(wb4_20250810_pr!B$1122:B$1395,U4) -> 2
A5: 3 | B5: PR層 | C5: /wb[cw]/wb[cw]_stage/ | D5: ./webbroker3.war/WEB-INF/classes/webbroker3/web/beans/ | E5: WEB3XTradeSessionUpdate0FEqBean.class | F5: 1562 | G5: 45937.653 | H5: ■PB00201704_0FQUICK連携対応 | I5: 変更 | J5: 通常 | K5: 0C | L5: [ap][wb] | U5: =SUBSTITUTE(SUBSTITUTE(D5&"/"&E5,"//","/"),"./webbroker3.war/",) -> WEB-INF/classes/webbroker3/web/beans/WEB3XTradeSessionUpdate0FEqBean.class | V5: =COUNTIF(wb4_20250810_pr!B$1122:B$1395,U5) -> 0
A6: 4 | B6: PR層 | C6: /wb[cw]/wb[cw]_stage/ | D6: ./webbroker3.war/WEB-INF/classes/webbroker3/web/define/ | E6: AA_JSPFileNameConst.class | F6: 3311 | G6: 45937.653 | H6: ■PB00201704_0FQUICK連携対応 | I6: 変更 | J6: 通常 | K6: 0C | L6: [ap][wb] | U6: =SUBSTITUTE(SUBSTITUTE(D6&"/"&E6,"//","/"),"./webbroker3.war/",) -> WEB-INF/classes/webbroker3/web/define/AA_JSPFileNameConst.class | V6: =COUNTIF(wb4_20250810_pr!B$1122:B$1395,U6) -> 2
A7: 5 | B7: PR層 | C7: /wb[cw]/wb[cw]_stage/ | D7: ./webbroker3.war/WEB-INF/src/webbroker3/web/beans/ | E7: application.xml | F7: 778230 | G7: 45937.653 | H7: ■PB00201704_0FQUICK連携対応 | I7: 変更 | J7: 通常 | K7: 0C | L7: [ap][wb] | U7: =SUBSTITUTE(SUBSTITUTE(D7&"/"&E7,"//","/"),"./webbroker3.war/",) -> WEB-INF/src/webbroker3/web/beans/application.xml | V7: =COUNTIF(wb4_20250810_pr!B$1122:B$1395,U7) -> 0

Sheet 第一生命保険
A1: モジュール情報 | K1: 配信 | L1: 同期 | M1: SVN | N1: 移行フェーズ | R1: 参考
A2: No | B2: サーバー | C2: ディレクトリ | E2: File名 | F2: Size | G2: TimeStamp | H2: 機能名 | I2: 修正 区分 | J2: ＵＰ区分 | K2: 環境 | M2: リビジョン | N2: UP予定日 | O2: UP区分 | P2: UP担当者 | Q2: ユーザID | R2: 変更概要（※案件名を記入） | S2: 備考（※定型案件の場合「定型案件」と記入） | X2: memo
A3: 1 | B3: PR層 | C3: /wb[cw]/wb[cw]_stage/ | D3: ./webbroker3.war/WEB-INF/classes/webbroker3/web/beans/pc/accinfo/ | E3: WEB3PcAccInfoMfaPskRegistCompleteBean.class | F3: 2062 | G3: 46211.782 | H3: ■PB00202136_44パスキー未登録顧客のSSO不可対応 | I3: 変更 | J3: 通常 | K3: 0G | L3: [ap][wb] | U3: =SUBSTITUTE(SUBSTITUTE(D3&"/"&E3,"//","/"),"./webbroker3.war/",) -> WEB-INF/classes/webbroker3/web/beans/pc/accinfo/WEB3PcAccInfoMfaPskRegistCompleteBean.class | V3: =COUNTIF(wb4_20250810_pr!B$2465:B$2749,U3) -> 0
A4: 2 | B4: PR層 | C4: /wb[cw]/wb[cw]_stage/ | D4: ./webbroker3.war/WEB-INF/classes/webbroker3/web/define/ | E4: CodeValueConst.class | F4: 117586 | G4: 46211.782 | H4: ■PB00202136_44パスキー未登録顧客のSSO不可対応 | I4: 変更 | J4: 通常 | K4: 0G | L4: [ap][wb] | U4: =SUBSTITUTE(SUBSTITUTE(D4&"/"&E4,"//","/"),"./webbroker3.war/",) -> WEB-INF/classes/webbroker3/web/define/CodeValueConst.class | V4: =COUNTIF(wb4_20250810_pr!B$2465:B$2749,U4) -> 2
A5: 3 | B5: PR層 | C5: /wb[cw]/wb[cw]_stage/ | D5: ./webbroker3.war/WEB-INF/classes/webbroker3/web/beans/ | E5: WEB3XTradeSessionUpdate0FEqBean.class | F5: 1562 | G5: 45937.653 | H5: ■PB00201704_0FQUICK連携対応 | I5: 変更 | J5: 通常 | K5: 0G | L5: [ap][wb] | U5: =SUBSTITUTE(SUBSTITUTE(D5&"/"&E5,"//","/"),"./webbroker3.war/",) -> WEB-INF/classes/webbroker3/web/beans/WEB3XTradeSessionUpdate0FEqBean.class | V5: =COUNTIF(wb4_20250810_pr!B$2465:B$2749,U5) -> 0
A6: 4 | B6: PR層 | C6: /wb[cw]/wb[cw]_stage/ | D6: ./webbroker3.war/WEB-INF/classes/webbroker3/web/define/ | E6: AA_JSPFileNameConst.class | F6: 3311 | G6: 45937.653 | H6: ■PB00201704_0FQUICK連携対応 | I6: 変更 | J6: 通常 | K6: 0G | L6: [ap][wb] | U6: =SUBSTITUTE(SUBSTITUTE(D6&"/"&E6,"//","/"),"./webbroker3.war/",) -> WEB-INF/classes/webbroker3/web/define/AA_JSPFileNameConst.class | V6: =COUNTIF(wb4_20250810_pr!B$2465:B$2749,U6) -> 2
A7: 5 | B7: PR層 | C7: /wb[cw]/wb[cw]_stage/ | D7: ./webbroker3.war/WEB-INF/src/webbroker3/web/beans/ | E7: application.xml | F7: 778230 | G7: 45937.653 | H7: ■PB00201704_0FQUICK連携対応 | I7: 変更 | J7: 通常 | K7: 0G | L7: [ap][wb] | U7: =SUBSTITUTE(SUBSTITUTE(D7&"/"&E7,"//","/"),"./webbroker3.war/",) -> WEB-INF/src/webbroker3/web/beans/application.xml | V7: =COUNTIF(wb4_20250810_pr!B$2465:B$2749,U7) -> 0

Sheet 大和コネクト証券
A1: モジュール情報 | K1: 配信 | L1: 同期 | M1: SVN | N1: 移行フェーズ | R1: 参考
A2: No | B2: サーバー | C2: ディレクトリ | E2: File名 | F2: Size | G2: TimeStamp | H2: 機能名 | I2: 修正 区分 | J2: ＵＰ区分 | K2: 環境 | M2: リビジョン | N2: UP予定日 | O2: UP区分 | P2: UP担当者 | Q2: ユーザID | R2: 変更概要（※案件名を記入） | S2: 備考（※定型案件の場合「定型案件」と記入） | X2: memo
A3: 1 | B3: PR層 | C3: /wb[cw]/wb[cw]_stage/ | D3: ./webbroker3.war/WEB-INF/classes/webbroker3/web/beans/pc/accinfo/ | E3: WEB3PcAccInfoMfaPskRegistCompleteBean.class | F3: 2062 | G3: 46211.782 | H3: ■PB00202136_44パスキー未登録顧客のSSO不可対応 | I3: 変更 | J3: 通常 | K3: 46 | L3: [ap][wb] | U3: =SUBSTITUTE(SUBSTITUTE(D3&"/"&E3,"//","/"),"./webbroker3.war/",) -> WEB-INF/classes/webbroker3/web/beans/pc/accinfo/WEB3PcAccInfoMfaPskRegistCompleteBean.class | V3: =COUNTIF(wb4_20250810_pr!B$2750:B$2959,U3) -> 0
A4: 2 | B4: PR層 | C4: /wb[cw]/wb[cw]_stage/ | D4: ./webbroker3.war/WEB-INF/classes/webbroker3/web/define/ | E4: CodeValueConst.class | F4: 117586 | G4: 46211.782 | H4: ■PB00202136_44パスキー未登録顧客のSSO不可対応 | I4: 変更 | J4: 通常 | K4: 46 | L4: [ap][wb] | U4: =SUBSTITUTE(SUBSTITUTE(D4&"/"&E4,"//","/"),"./webbroker3.war/",) -> WEB-INF/classes/webbroker3/web/define/CodeValueConst.class | V4: =COUNTIF(wb4_20250810_pr!B$2750:B$2959,U4) -> 2
A5: 3 | B5: PR層 | C5: /wb[cw]/wb[cw]_stage/ | D5: ./webbroker3.war/WEB-INF/classes/webbroker3/web/beans/ | E5: WEB3XTradeSessionUpdate0FEqBean.class | F5: 1562 | G5: 45937.653 | H5: ■PB00201704_0FQUICK連携対応 | I5: 変更 | J5: 通常 | K5: 46 | L5: [ap][wb] | U5: =SUBSTITUTE(SUBSTITUTE(D5&"/"&E5,"//","/"),"./webbroker3.war/",) -> WEB-INF/classes/webbroker3/web/beans/WEB3XTradeSessionUpdate0FEqBean.class | V5: =COUNTIF(wb4_20250810_pr!B$2750:B$2959,U5) -> 0
A6: 4 | B6: PR層 | C6: /wb[cw]/wb[cw]_stage/ | D6: ./webbroker3.war/WEB-INF/classes/webbroker3/web/define/ | E6: AA_JSPFileNameConst.class | F6: 3311 | G6: 45937.653 | H6: ■PB00201704_0FQUICK連携対応 | I6: 変更 | J6: 通常 | K6: 46 | L6: [ap][wb] | U6: =SUBSTITUTE(SUBSTITUTE(D6&"/"&E6,"//","/"),"./webbroker3.war/",) -> WEB-INF/classes/webbroker3/web/define/AA_JSPFileNameConst.class | V6: =COUNTIF(wb4_20250810_pr!B$2750:B$2959,U6) -> 0
A7: 5 | B7: PR層 | C7: /wb[cw]/wb[cw]_stage/ | D7: ./webbroker3.war/WEB-INF/src/webbroker3/web/beans/ | E7: application.xml | F7: 778230 | G7: 45937.653 | H7: ■PB00201704_0FQUICK連携対応 | I7: 変更 | J7: 通常 | K7: 46 | L7: [ap][wb] | U7: =SUBSTITUTE(SUBSTITUTE(D7&"/"&E7,"//","/"),"./webbroker3.war/",) -> WEB-INF/src/webbroker3/web/beans/application.xml | V7: =COUNTIF(wb4_20250810_pr!B$2750:B$2959,U7) -> 0

Sheet セゾン投信
A1: モジュール情報 | K1: 配信 | L1: 同期 | M1: SVN | N1: 移行フェーズ | R1: 参考
A2: No | B2: サーバー | C2: ディレクトリ | E2: File名 | F2: Size | G2: TimeStamp | H2: 機能名 | I2: 修正 区分 | J2: ＵＰ区分 | K2: 環境 | M2: リビジョン | N2: UP予定日 | O2: UP区分 | P2: UP担当者 | Q2: ユーザID | R2: 変更概要（※案件名を記入） | S2: 備考（※定型案件の場合「定型案件」と記入） | X2: memo
A3: 1 | B3: PR層 | C3: /wb[cw]/wb[cw]_stage/ | D3: ./webbroker3.war/WEB-INF/classes/webbroker3/web/beans/pc/accinfo/ | E3: WEB3PcAccInfoMfaPskRegistCompleteBean.class | F3: 2062 | G3: 46211.782 | H3: ■PB00202136_44パスキー未登録顧客のSSO不可対応 | I3: 変更 | J3: 通常 | K3: 0H | L3: [ap][wb] | U3: =SUBSTITUTE(SUBSTITUTE(D3&"/"&E3,"//","/"),"./webbroker3.war/",) -> WEB-INF/classes/webbroker3/web/beans/pc/accinfo/WEB3PcAccInfoMfaPskRegistCompleteBean.class | V3: =COUNTIF(wb4_20250810_pr!B$1396:B$1676,U3) -> 0
A4: 2 | B4: PR層 | C4: /wb[cw]/wb[cw]_stage/ | D4: ./webbroker3.war/WEB-INF/classes/webbroker3/web/define/ | E4: CodeValueConst.class | F4: 117586 | G4: 46211.782 | H4: ■PB00202136_44パスキー未登録顧客のSSO不可対応 | I4: 変更 | J4: 通常 | K4: 0H | L4: [ap][wb] | U4: =SUBSTITUTE(SUBSTITUTE(D4&"/"&E4,"//","/"),"./webbroker3.war/",) -> WEB-INF/classes/webbroker3/web/define/CodeValueConst.class | V4: =COUNTIF(wb4_20250810_pr!B$1396:B$1676,U4) -> 2
A5: 3 | B5: PR層 | C5: /wb[cw]/wb[cw]_stage/ | D5: ./webbroker3.war/WEB-INF/classes/webbroker3/web/beans/ | E5: WEB3XTradeSessionUpdate0FEqBean.class | F5: 1562 | G5: 45937.653 | H5: ■PB00201704_0FQUICK連携対応 | I5: 変更 | J5: 通常 | K5: 0H | L5: [ap][wb] | U5: =SUBSTITUTE(SUBSTITUTE(D5&"/"&E5,"//","/"),"./webbroker3.war/",) -> WEB-INF/classes/webbroker3/web/beans/WEB3XTradeSessionUpdate0FEqBean.class | V5: =COUNTIF(wb4_20250810_pr!B$1396:B$1676,U5) -> 0
A6: 4 | B6: PR層 | C6: /wb[cw]/wb[cw]_stage/ | D6: ./webbroker3.war/WEB-INF/classes/webbroker3/web/define/ | E6: AA_JSPFileNameConst.class | F6: 3311 | G6: 45937.653 | H6: ■PB00201704_0FQUICK連携対応 | I6: 変更 | J6: 通常 | K6: 0H | L6: [ap][wb] | U6: =SUBSTITUTE(SUBSTITUTE(D6&"/"&E6,"//","/"),"./webbroker3.war/",) -> WEB-INF/classes/webbroker3/web/define/AA_JSPFileNameConst.class | V6: =COUNTIF(wb4_20250810_pr!B$1396:B$1676,U6) -> 2
A7: 5 | B7: PR層 | C7: /wb[cw]/wb[cw]_stage/ | D7: ./webbroker3.war/WEB-INF/src/webbroker3/web/beans/ | E7: application.xml | F7: 778230 | G7: 45937.653 | H7: ■PB00201704_0FQUICK連携対応 | I7: 変更 | J7: 通常 | K7: 0H | L7: [ap][wb] | U7: =SUBSTITUTE(SUBSTITUTE(D7&"/"&E7,"//","/"),"./webbroker3.war/",) -> WEB-INF/src/webbroker3/web/beans/application.xml | V7: =COUNTIF(wb4_20250810_pr!B$1396:B$1676,U7) -> 0

Sheet マネックス証券
A1: モジュール情報 | K1: 配信 | L1: 同期 | M1: SVN | N1: 移行フェーズ | R1: 参考
A2: No | B2: サーバー | C2: ディレクトリ | E2: File名 | F2: Size | G2: TimeStamp | H2: 機能名 | I2: 修正 区分 | J2: ＵＰ区分 | K2: 環境 | M2: リビジョン | N2: UP予定日 | O2: UP区分 | P2: UP担当者 | Q2: ユーザID | R2: 変更概要（※案件名を記入） | S2: 備考（※定型案件の場合「定型案件」と記入） | X2: memo
A3: 1 | B3: PR層 | C3: /wb[cw]/wb[cw]_stage/ | D3: ./webbroker3.war/WEB-INF/classes/webbroker3/web/beans/pc/accinfo/ | E3: WEB3PcAccInfoMfaPskRegistCompleteBean.class | F3: 2062 | G3: 46211.782 | H3: ■PB00202136_44パスキー未登録顧客のSSO不可対応 | I3: 変更 | J3: 通常 | K3: 52 | L3: [ap][wb] | U3: =SUBSTITUTE(SUBSTITUTE(D3&"/"&E3,"//","/"),"./webbroker3.war/",) -> WEB-INF/classes/webbroker3/web/beans/pc/accinfo/WEB3PcAccInfoMfaPskRegistCompleteBean.class | V3: =COUNTIF(wb4_20250810_pr!B$1677:B$1958,U3) -> 0
A4: 2 | B4: PR層 | C4: /wb[cw]/wb[cw]_stage/ | D4: ./webbroker3.war/WEB-INF/classes/webbroker3/web/define/ | E4: CodeValueConst.class | F4: 117586 | G4: 46211.782 | H4: ■PB00202136_44パスキー未登録顧客のSSO不可対応 | I4: 変更 | J4: 通常 | K4: 52 | L4: [ap][wb] | U4: =SUBSTITUTE(SUBSTITUTE(D4&"/"&E4,"//","/"),"./webbroker3.war/",) -> WEB-INF/classes/webbroker3/web/define/CodeValueConst.class | V4: =COUNTIF(wb4_20250810_pr!B$1677:B$1958,U4) -> 2
A5: 3 | B5: PR層 | C5: /wb[cw]/wb[cw]_stage/ | D5: ./webbroker3.war/WEB-INF/classes/webbroker3/web/beans/ | E5: WEB3XTradeSessionUpdate0FEqBean.class | F5: 1562 | G5: 45937.653 | H5: ■PB00201704_0FQUICK連携対応 | I5: 変更 | J5: 通常 | K5: 52 | L5: [ap][wb] | U5: =SUBSTITUTE(SUBSTITUTE(D5&"/"&E5,"//","/"),"./webbroker3.war/",) -> WEB-INF/classes/webbroker3/web/beans/WEB3XTradeSessionUpdate0FEqBean.class | V5: =COUNTIF(wb4_20250810_pr!B$1677:B$1958,U5) -> 0
A6: 4 | B6: PR層 | C6: /wb[cw]/wb[cw]_stage/ | D6: ./webbroker3.war/WEB-INF/classes/webbroker3/web/define/ | E6: AA_JSPFileNameConst.class | F6: 3311 | G6: 45937.653 | H6: ■PB00201704_0FQUICK連携対応 | I6: 変更 | J6: 通常 | K6: 52 | L6: [ap][wb] | U6: =SUBSTITUTE(SUBSTITUTE(D6&"/"&E6,"//","/"),"./webbroker3.war/",) -> WEB-INF/classes/webbroker3/web/define/AA_JSPFileNameConst.class | V6: =COUNTIF(wb4_20250810_pr!B$1677:B$1958,U6) -> 2
A7: 5 | B7: PR層 | C7: /wb[cw]/wb[cw]_stage/ | D7: ./webbroker3.war/WEB-INF/src/webbroker3/web/beans/ | E7: application.xml | F7: 778230 | G7: 45937.653 | H7: ■PB00201704_0FQUICK連携対応 | I7: 変更 | J7: 通常 | K7: 52 | L7: [ap][wb] | U7: =SUBSTITUTE(SUBSTITUTE(D7&"/"&E7,"//","/"),"./webbroker3.war/",) -> WEB-INF/src/webbroker3/web/beans/application.xml | V7: =COUNTIF(wb4_20250810_pr!B$1677:B$1958,U7) -> 0

Sheet リテラ・クレア証券対面ネット
A1: モジュール情報 | K1: 配信 | L1: 同期 | M1: SVN | N1: 移行フェーズ | R1: 参考
A2: No | B2: サーバー | C2: ディレクトリ | E2: File名 | F2: Size | G2: TimeStamp | H2: 機能名 | I2: 修正 区分 | J2: ＵＰ区分 | K2: 環境 | M2: リビジョン | N2: UP予定日 | O2: UP区分 | P2: UP担当者 | Q2: ユーザID | R2: 変更概要（※案件名を記入） | S2: 備考（※定型案件の場合「定型案件」と記入） | X2: memo
A3: 1 | B3: PR層 | C3: /wb[cw]/wb[cw]_stage/ | D3: ./webbroker3.war/WEB-INF/classes/webbroker3/web/beans/pc/accinfo/ | E3: WEB3PcAccInfoMfaPskRegistCompleteBean.class | F3: 2062 | G3: 46211.782 | H3: ■PB00202136_44パスキー未登録顧客のSSO不可対応 | I3: 変更 | J3: 通常 | K3: 09 | L3: [ap][wb] | U3: =SUBSTITUTE(SUBSTITUTE(D3&"/"&E3,"//","/"),"./webbroker3.war/",) -> WEB-INF/classes/webbroker3/web/beans/pc/accinfo/WEB3PcAccInfoMfaPskRegistCompleteBean.class | V3: =COUNTIF(wb4_20250810_pr!B$758:B$1033,U3) -> 0
A4: 2 | B4: PR層 | C4: /wb[cw]/wb[cw]_stage/ | D4: ./webbroker3.war/WEB-INF/classes/webbroker3/web/define/ | E4: CodeValueConst.class | F4: 117586 | G4: 46211.782 | H4: ■PB00202136_44パスキー未登録顧客のSSO不可対応 | I4: 変更 | J4: 通常 | K4: 09 | L4: [ap][wb] | U4: =SUBSTITUTE(SUBSTITUTE(D4&"/"&E4,"//","/"),"./webbroker3.war/",) -> WEB-INF/classes/webbroker3/web/define/CodeValueConst.class | V4: =COUNTIF(wb4_20250810_pr!B$758:B$1033,U4) -> 2
A5: 3 | B5: PR層 | C5: /wb[cw]/wb[cw]_stage/ | D5: ./webbroker3.war/WEB-INF/classes/webbroker3/web/beans/ | E5: WEB3XTradeSessionUpdate0FEqBean.class | F5: 1562 | G5: 45937.653 | H5: ■PB00201704_0FQUICK連携対応 | I5: 変更 | J5: 通常 | K5: 09 | L5: [ap][wb] | U5: =SUBSTITUTE(SUBSTITUTE(D5&"/"&E5,"//","/"),"./webbroker3.war/",) -> WEB-INF/classes/webbroker3/web/beans/WEB3XTradeSessionUpdate0FEqBean.class | V5: =COUNTIF(wb4_20250810_pr!B$758:B$1033,U5) -> 0
A6: 4 | B6: PR層 | C6: /wb[cw]/wb[cw]_stage/ | D6: ./webbroker3.war/WEB-INF/classes/webbroker3/web/define/ | E6: AA_JSPFileNameConst.class | F6: 3311 | G6: 45937.653 | H6: ■PB00201704_0FQUICK連携対応 | I6: 変更 | J6: 通常 | K6: 09 | L6: [ap][wb] | U6: =SUBSTITUTE(SUBSTITUTE(D6&"/"&E6,"//","/"),"./webbroker3.war/",) -> WEB-INF/classes/webbroker3/web/define/AA_JSPFileNameConst.class | V6: =COUNTIF(wb4_20250810_pr!B$758:B$1033,U6) -> 2
A7: 5 | B7: PR層 | C7: /wb[cw]/wb[cw]_stage/ | D7: ./webbroker3.war/WEB-INF/src/webbroker3/web/beans/ | E7: application.xml | F7: 778230 | G7: 45937.653 | H7: ■PB00201704_0FQUICK連携対応 | I7: 変更 | J7: 通常 | K7: 09 | L7: [ap][wb] | U7: =SUBSTITUTE(SUBSTITUTE(D7&"/"&E7,"//","/"),"./webbroker3.war/",) -> WEB-INF/src/webbroker3/web/beans/application.xml | V7: =COUNTIF(wb4_20250810_pr!B$758:B$1033,U7) -> 0

Sheet SBIネオトレード証券
A1: モジュール情報 | K1: 配信 | L1: 同期 | M1: SVN | N1: 移行フェーズ | R1: 参考
A2: No | B2: サーバー | C2: ディレクトリ | E2: File名 | F2: Size | G2: TimeStamp | H2: 機能名 | I2: 修正 区分 | J2: ＵＰ区分 | K2: 環境 | M2: リビジョン | N2: UP予定日 | O2: UP区分 | P2: UP担当者 | Q2: ユーザID | R2: 変更概要（※案件名を記入） | S2: 備考（※定型案件の場合「定型案件」と記入） | X2: memo
A3: 1 | B3: PR層 | C3: /wb[cw]/wb[cw]_stage/ | D3: ./webbroker3.war/WEB-INF/classes/webbroker3/web/beans/ | E3: WEB3XTradeSessionUpdate0FEqBean.class | F3: 1562 | G3: 45937.653 | H3: ■PB00201704_0FQUICK連携対応 | I3: 変更 | J3: 通常 | K3: 44 | L3: [ap][wb] | U3: =SUBSTITUTE(SUBSTITUTE(D3&"/"&E3,"//","/"),"./webbroker3.war/",) -> WEB-INF/classes/webbroker3/web/beans/WEB3XTradeSessionUpdate0FEqBean.class | V3: =COUNTIF(wb4_20250810_pr!B$1034:B$1121,U3) -> 0
A4: 2 | B4: PR層 | C4: /wb[cw]/wb[cw]_stage/ | D4: ./webbroker3.war/WEB-INF/classes/webbroker3/web/define/ | E4: AA_JSPFileNameConst.class | F4: 3311 | G4: 45937.653 | H4: ■PB00201704_0FQUICK連携対応 | I4: 変更 | J4: 通常 | K4: 44 | L4: [ap][wb] | U4: =SUBSTITUTE(SUBSTITUTE(D4&"/"&E4,"//","/"),"./webbroker3.war/",) -> WEB-INF/classes/webbroker3/web/define/AA_JSPFileNameConst.class | V4: =COUNTIF(wb4_20250810_pr!B$1034:B$1121,U4) -> 0
A5: 3 | B5: PR層 | C5: /wb[cw]/wb[cw]_stage/ | D5: ./webbroker3.war/WEB-INF/src/webbroker3/web/beans/ | E5: application.xml | F5: 778230 | G5: 45937.653 | H5: ■PB00201704_0FQUICK連携対応 | I5: 変更 | J5: 通常 | K5: 44 | L5: [ap][wb] | U5: =SUBSTITUTE(SUBSTITUTE(D5&"/"&E5,"//","/"),"./webbroker3.war/",) -> WEB-INF/src/webbroker3/web/beans/application.xml | V5: =COUNTIF(wb4_20250810_pr!B$1034:B$1121,U5) -> 0

Sheet OKB証券
A1: モジュール情報 | K1: 配信 | L1: 同期 | M1: SVN | N1: 移行フェーズ | R1: 参考
A2: No | B2: サーバー | C2: ディレクトリ | E2: File名 | F2: Size | G2: TimeStamp | H2: 機能名 | I2: 修正 区分 | J2: ＵＰ区分 | K2: 環境 | M2: リビジョン | N2: UP予定日 | O2: UP区分 | P2: UP担当者 | Q2: ユーザID | R2: 変更概要（※案件名を記入） | S2: 備考（※定型案件の場合「定型案件」と記入） | X2: memo
A3: 1 | B3: PR層 | C3: /wb[cw]/wb[cw]_stage/ | D3: ./webbroker3.war/WEB-INF/classes/webbroker3/web/beans/pc/accinfo/ | E3: WEB3PcAccInfoMfaPskRegistCompleteBean.class | F3: 2062 | G3: 46211.782 | H3: ■PB00202136_44パスキー未登録顧客のSSO不可対応 | I3: 変更 | J3: 通常 | K3: 0F | L3: [ap][wb] | U3: =SUBSTITUTE(SUBSTITUTE(D3&"/"&E3,"//","/"),"./webbroker3.war/",) -> WEB-INF/classes/webbroker3/web/beans/pc/accinfo/WEB3PcAccInfoMfaPskRegistCompleteBean.class | V3: =COUNTIF(wb4_20250810_pr!B$1959:B$2204,U3) -> 0
A4: 2 | B4: PR層 | C4: /wb[cw]/wb[cw]_stage/ | D4: ./webbroker3.war/WEB-INF/classes/webbroker3/web/define/ | E4: CodeValueConst.class | F4: 117586 | G4: 46211.782 | H4: ■PB00202136_44パスキー未登録顧客のSSO不可対応 | I4: 変更 | J4: 通常 | K4: 0F | L4: [ap][wb] | U4: =SUBSTITUTE(SUBSTITUTE(D4&"/"&E4,"//","/"),"./webbroker3.war/",) -> WEB-INF/classes/webbroker3/web/define/CodeValueConst.class | V4: =COUNTIF(wb4_20250810_pr!B$1959:B$2204,U4) -> 2

Sheet 安藤証券
A1: モジュール情報 | K1: 配信 | L1: 同期 | M1: SVN | N1: 移行フェーズ | R1: 参考
A2: No | B2: サーバー | C2: ディレクトリ | E2: File名 | F2: Size | G2: TimeStamp | H2: 機能名 | I2: 修正 区分 | J2: ＵＰ区分 | K2: 環境 | M2: リビジョン | N2: UP予定日 | O2: UP区分 | P2: UP担当者 | Q2: ユーザID | R2: 変更概要（※案件名を記入） | S2: 備考（※定型案件の場合「定型案件」と記入） | X2: memo
A3: 1 | B3: PR層 | C3: /wb[cw]/wb[cw]_stage/ | D3: ./webbroker3.war/WEB-INF/classes/webbroker3/web/beans/pc/accinfo/ | E3: WEB3PcAccInfoMfaPskRegistCompleteBean.class | F3: 2062 | G3: 46211.782 | H3: ■PB00202136_44パスキー未登録顧客のSSO不可対応 | I3: 変更 | J3: 通常 | K3: 0X | L3: [ap][wb] | U3: =SUBSTITUTE(SUBSTITUTE(D3&"/"&E3,"//","/"),"./webbroker3.war/",) -> WEB-INF/classes/webbroker3/web/beans/pc/accinfo/WEB3PcAccInfoMfaPskRegistCompleteBean.class | V3: =COUNTIF(wb4_20250810_pr!B$2205:B$2464,U3) -> 0
A4: 2 | B4: PR層 | C4: /wb[cw]/wb[cw]_stage/ | D4: ./webbroker3.war/WEB-INF/classes/webbroker3/web/define/ | E4: CodeValueConst.class | F4: 117586 | G4: 46211.782 | H4: ■PB00202136_44パスキー未登録顧客のSSO不可対応 | I4: 変更 | J4: 通常 | K4: 0X | L4: [ap][wb] | U4: =SUBSTITUTE(SUBSTITUTE(D4&"/"&E4,"//","/"),"./webbroker3.war/",) -> WEB-INF/classes/webbroker3/web/define/CodeValueConst.class | V4: =COUNTIF(wb4_20250810_pr!B$2205:B$2464,U4) -> 2
A5: 3 | B5: PR層 | C5: /wb[cw]/wb[cw]_stage/ | D5: ./webbroker3.war/WEB-INF/classes/webbroker3/web/beans/ | E5: WEB3XTradeSessionUpdate0FEqBean.class | F5: 1562 | G5: 45937.653 | H5: ■PB00201704_0FQUICK連携対応 | I5: 変更 | J5: 通常 | K5: 0X | L5: [ap][wb] | U5: =SUBSTITUTE(SUBSTITUTE(D5&"/"&E5,"//","/"),"./webbroker3.war/",) -> WEB-INF/classes/webbroker3/web/beans/WEB3XTradeSessionUpdate0FEqBean.class | V5: =COUNTIF(wb4_20250810_pr!B$2205:B$2464,U5) -> 0
A6: 4 | B6: PR層 | C6: /wb[cw]/wb[cw]_stage/ | D6: ./webbroker3.war/WEB-INF/classes/webbroker3/web/define/ | E6: AA_JSPFileNameConst.class | F6: 3311 | G6: 45937.653 | H6: ■PB00201704_0FQUICK連携対応 | I6: 変更 | J6: 通常 | K6: 0X | L6: [ap][wb] | U6: =SUBSTITUTE(SUBSTITUTE(D6&"/"&E6,"//","/"),"./webbroker3.war/",) -> WEB-INF/classes/webbroker3/web/define/AA_JSPFileNameConst.class | V6: =COUNTIF(wb4_20250810_pr!B$2205:B$2464,U6) -> 0
A7: 5 | B7: PR層 | C7: /wb[cw]/wb[cw]_stage/ | D7: ./webbroker3.war/WEB-INF/src/webbroker3/web/beans/ | E7: application.xml | F7: 778230 | G7: 45937.653 | H7: ■PB00201704_0FQUICK連携対応 | I7: 変更 | J7: 通常 | K7: 0X | L7: [ap][wb] | U7: =SUBSTITUTE(SUBSTITUTE(D7&"/"&E7,"//","/"),"./webbroker3.war/",) -> WEB-INF/src/webbroker3/web/beans/application.xml | V7: =COUNTIF(wb4_20250810_pr!B$2205:B$2464,U7) -> 0

Sheet フィデリティ証券
A1: モジュール情報 | K1: 配信 | L1: 同期 | M1: SVN | N1: 移行フェーズ | R1: 参考
A2: No | B2: サーバー | C2: ディレクトリ | E2: File名 | F2: Size | G2: TimeStamp | H2: 機能名 | I2: 修正 区分 | J2: ＵＰ区分 | K2: 環境 | M2: リビジョン | N2: UP予定日 | O2: UP区分 | P2: UP担当者 | Q2: ユーザID | R2: 変更概要（※案件名を記入） | S2: 備考（※定型案件の場合「定型案件」と記入）
A3: 1 | B3: PR層 | C3: /wb[cw]/wb[cw]_stage/ | D3: ./webbroker3.war/WEB-INF/classes/webbroker3/web/beans/pc/accinfo/ | E3: WEB3PcAccInfoMfaPskRegistCompleteBean.class | F3: 2062 | G3: 46211.782 | H3: ■PB00202136_44パスキー未登録顧客のSSO不可対応 | I3: 変更 | J3: 通常 | K3: 08 | L3: [ap][wb] | U3: =SUBSTITUTE(SUBSTITUTE(D3&"/"&E3,"//","/"),"./webbroker3.war/",) -> WEB-INF/classes/webbroker3/web/beans/pc/accinfo/WEB3PcAccInfoMfaPskRegistCompleteBean.class
A4: 2 | B4: PR層 | C4: /wb[cw]/wb[cw]_stage/ | D4: ./webbroker3.war/WEB-INF/classes/webbroker3/web/define/ | E4: CodeValueConst.class | F4: 117586 | G4: 46211.782 | H4: ■PB00202136_44パスキー未登録顧客のSSO不可対応 | I4: 変更 | J4: 通常 | K4: 08 | L4: [ap][wb] | U4: =SUBSTITUTE(SUBSTITUTE(D4&"/"&E4,"//","/"),"./webbroker3.war/",) -> WEB-INF/classes/webbroker3/web/define/CodeValueConst.class
A5: 3 | B5: PR層 | C5: /wb[cw]/wb[cw]_stage/ | D5: ./webbroker3.war/WEB-INF/classes/webbroker3/web/beans/ | E5: WEB3XTradeSessionUpdate0FEqBean.class | F5: 1562 | G5: 45937.653 | H5: ■PB00201704_0FQUICK連携対応 | I5: 変更 | J5: 通常 | K5: 08 | L5: [ap][wb] | U5: =SUBSTITUTE(SUBSTITUTE(D5&"/"&E5,"//","/"),"./webbroker3.war/",) -> WEB-INF/classes/webbroker3/web/beans/WEB3XTradeSessionUpdate0FEqBean.class
A6: 4 | B6: PR層 | C6: /wb[cw]/wb[cw]_stage/ | D6: ./webbroker3.war/WEB-INF/classes/webbroker3/web/define/ | E6: AA_JSPFileNameConst.class | F6: 3311 | G6: 45937.653 | H6: ■PB00201704_0FQUICK連携対応 | I6: 変更 | J6: 通常 | K6: 08 | L6: [ap][wb] | U6: =SUBSTITUTE(SUBSTITUTE(D6&"/"&E6,"//","/"),"./webbroker3.war/",) -> WEB-INF/classes/webbroker3/web/define/AA_JSPFileNameConst.class
A7: 5 | B7: PR層 | C7: /wb[cw]/wb[cw]_stage/ | D7: ./webbroker3.war/WEB-INF/src/webbroker3/web/beans/ | E7: application.xml | F7: 778230 | G7: 45937.653 | H7: ■PB00201704_0FQUICK連携対応 | I7: 変更 | J7: 通常 | K7: 08 | L7: [ap][wb] | U7: =SUBSTITUTE(SUBSTITUTE(D7&"/"&E7,"//","/"),"./webbroker3.war/",) -> WEB-INF/src/webbroker3/web/beans/application.xml

Sheet リッチWEB
A1: モジュール情報 | K1: 配信 | L1: 同期 | M1: SVN | N1: 移行フェーズ | R1: 参考
A2: No | B2: サーバー | C2: ディレクトリ | E2: File名 | F2: Size | G2: TimeStamp | H2: 機能名 | I2: 修正 区分 | J2: ＵＰ区分 | K2: 環境 | M2: リビジョン | N2: UP予定日 | O2: UP区分 | P2: UP担当者 | Q2: ユーザID | R2: 変更概要（※案件名を記入） | S2: 備考（※定型案件の場合「定型案件」と記入）
A3: 1 | B3: PR層 | C3: /wb[cw]/wb[cw]_stage/ | D3: ./webbroker3.war/WEB-INF/classes/webbroker3/web/beans/pc/accinfo/ | E3: WEB3PcAccInfoMfaPskRegistCompleteBean.class | F3: 2062 | G3: 46211.782 | H3: ■PB00202136_44パスキー未登録顧客のSSO不可対応 | I3: 変更 | J3: 通常 | K3: 44 rch | L3: [ap][wb] | U3: =SUBSTITUTE(SUBSTITUTE(D3&"/"&E3,"//","/"),"./webbroker3.war/",) -> WEB-INF/classes/webbroker3/web/beans/pc/accinfo/WEB3PcAccInfoMfaPskRegistCompleteBean.class
A4: 2 | B4: PR層 | C4: /wb[cw]/wb[cw]_stage/ | D4: ./webbroker3.war/WEB-INF/classes/webbroker3/web/define/ | E4: CodeValueConst.class | F4: 117586 | G4: 46211.782 | H4: ■PB00202136_44パスキー未登録顧客のSSO不可対応 | I4: 変更 | J4: 通常 | K4: 44 rch | L4: [ap][wb] | U4: =SUBSTITUTE(SUBSTITUTE(D4&"/"&E4,"//","/"),"./webbroker3.war/",) -> WEB-INF/classes/webbroker3/web/define/CodeValueConst.class
A5: 3 | B5: PR層 | C5: /wb[cw]/wb[cw]_stage/ | D5: ./webbroker3.war/WEB-INF/classes/webbroker3/web/beans/ | E5: WEB3XTradeSessionUpdate0FEqBean.class | F5: 1562 | G5: 45937.653 | H5: ■PB00201704_0FQUICK連携対応 | I5: 変更 | J5: 通常 | K5: 44 rch | L5: [ap][wb] | U5: =SUBSTITUTE(SUBSTITUTE(D5&"/"&E5,"//","/"),"./webbroker3.war/",) -> WEB-INF/classes/webbroker3/web/beans/WEB3XTradeSessionUpdate0FEqBean.class
A6: 4 | B6: PR層 | C6: /wb[cw]/wb[cw]_stage/ | D6: ./webbroker3.war/WEB-INF/classes/webbroker3/web/define/ | E6: AA_JSPFileNameConst.class | F6: 3311 | G6: 45937.653 | H6: ■PB00201704_0FQUICK連携対応 | I6: 変更 | J6: 通常 | K6: 44 rch | L6: [ap][wb] | U6: =SUBSTITUTE(SUBSTITUTE(D6&"/"&E6,"//","/"),"./webbroker3.war/",) -> WEB-INF/classes/webbroker3/web/define/AA_JSPFileNameConst.class
A7: 5 | B7: PR層 | C7: /wb[cw]/wb[cw]_stage/ | D7: ./webbroker3.war/WEB-INF/src/webbroker3/web/beans/ | E7: application.xml | F7: 778230 | G7: 45937.653 | H7: ■PB00201704_0FQUICK連携対応 | I7: 変更 | J7: 通常 | K7: 44 rch | L7: [ap][wb] | U7: =SUBSTITUTE(SUBSTITUTE(D7&"/"&E7,"//","/"),"./webbroker3.war/",) -> WEB-INF/src/webbroker3/web/beans/application.xml
